{"cameraMode":{"drawMode":0,"name":"Shaded","section":"Shading Mode"},"sceneLighting":true,"audioPlay":false,"sceneViewState":{"showFog":true,"showMaterialUpdate":false,"showSkybox":false,"showFlares":true,"showImageEffects":true,"showParticleSystems":true,"showVisualEffectGraphs":true,"m_FxEnabled":true},"in2DMode":false,"pivot":{"x":-8.892513275146485,"y":-7.903346061706543,"z":36.087188720703128},"rotation":{"x":0.3588348627090454,"y":-0.2830072343349457,"z":0.11515849828720093,"w":0.8819936513900757},"size":9.288576126098633,"orthographic":false}